{
	"configurations" : 
	[
		{
			"directories" : 
			[
				{
					"build" : ".",
					"childIndexes" : 
					[
						1,
						2
					],
					"jsonFile" : "directory-.-Release-f5ebdc15457944623624.json",
					"minimumCMakeVersion" : 
					{
						"string" : "3.10"
					},
					"projectIndex" : 0,
					"source" : "."
				},
				{
					"build" : "src",
					"jsonFile" : "directory-src-Release-b6cf2213fc5053b67c22.json",
					"minimumCMakeVersion" : 
					{
						"string" : "3.10"
					},
					"parentIndex" : 0,
					"projectIndex" : 0,
					"source" : "src",
					"targetIndexes" : 
					[
						0,
						3
					]
				},
				{
					"build" : "test",
					"jsonFile" : "directory-test-Release-451c0598f41488bb20b9.json",
					"minimumCMakeVersion" : 
					{
						"string" : "3.10"
					},
					"parentIndex" : 0,
					"projectIndex" : 0,
					"source" : "test",
					"targetIndexes" : 
					[
						1,
						2
					]
				}
			],
			"name" : "Release",
			"projects" : 
			[
				{
					"directoryIndexes" : 
					[
						0,
						1,
						2
					],
					"name" : "ws_server",
					"targetIndexes" : 
					[
						0,
						1,
						2,
						3
					]
				}
			],
			"targets" : 
			[
				{
					"directoryIndex" : 1,
					"id" : "core::@145eef247bfb46b6828c",
					"jsonFile" : "target-core-Release-74d7fe66e07272dccce0.json",
					"name" : "core",
					"projectIndex" : 0
				},
				{
					"directoryIndex" : 2,
					"id" : "test_config::@36f028580bb02cc8272a",
					"jsonFile" : "target-test_config-Release-6ffd3222c0efda22bc4b.json",
					"name" : "test_config",
					"projectIndex" : 0
				},
				{
					"directoryIndex" : 2,
					"id" : "tests::@36f028580bb02cc8272a",
					"jsonFile" : "target-tests-Release-32be0e06041d50dc54cd.json",
					"name" : "tests",
					"projectIndex" : 0
				},
				{
					"directoryIndex" : 1,
					"id" : "ws_server::@145eef247bfb46b6828c",
					"jsonFile" : "target-ws_server-Release-2cdc351583090feea1a1.json",
					"name" : "ws_server",
					"projectIndex" : 0
				}
			]
		}
	],
	"kind" : "codemodel",
	"paths" : 
	{
		"build" : "/home/qing/CodeJourney/snorlaxchat/server/build",
		"source" : "/home/qing/CodeJourney/snorlaxchat/server"
	},
	"version" : 
	{
		"major" : 2,
		"minor" : 6
	}
}
